swaggyjenkins/__init__.py
swaggyjenkins/api_client.py
swaggyjenkins/api_response.py
swaggyjenkins/configuration.py
swaggyjenkins/exceptions.py
swaggyjenkins/py.typed
swaggyjenkins/rest.py
swaggyjenkins/api/__init__.py
swaggyjenkins/api/base_api.py
swaggyjenkins/api/blue_ocean_api.py
swaggyjenkins/api/remote_access_api.py
swaggyjenkins/models/__init__.py
swaggyjenkins/models/all_view.py
swaggyjenkins/models/branch_impl.py
swaggyjenkins/models/branch_impllinks.py
swaggyjenkins/models/branch_implpermissions.py
swaggyjenkins/models/cause_action.py
swaggyjenkins/models/cause_user_id_cause.py
swaggyjenkins/models/classes_by_class.py
swaggyjenkins/models/clock_difference.py
swaggyjenkins/models/computer_set.py
swaggyjenkins/models/default_crumb_issuer.py
swaggyjenkins/models/disk_space_monitor_descriptor_disk_space.py
swaggyjenkins/models/empty_change_log_set.py
swaggyjenkins/models/extension_class_container_impl1.py
swaggyjenkins/models/extension_class_container_impl1links.py
swaggyjenkins/models/extension_class_container_impl1map.py
swaggyjenkins/models/extension_class_impl.py
swaggyjenkins/models/extension_class_impllinks.py
swaggyjenkins/models/favorite_impl.py
swaggyjenkins/models/favorite_impllinks.py
swaggyjenkins/models/free_style_build.py
swaggyjenkins/models/free_style_project.py
swaggyjenkins/models/free_style_projectactions.py
swaggyjenkins/models/free_style_projecthealth_report.py
swaggyjenkins/models/generic_resource.py
swaggyjenkins/models/github_content.py
swaggyjenkins/models/github_file.py
swaggyjenkins/models/github_organization.py
swaggyjenkins/models/github_organizationlinks.py
swaggyjenkins/models/github_repositories.py
swaggyjenkins/models/github_repositorieslinks.py
swaggyjenkins/models/github_repository.py
swaggyjenkins/models/github_repositorylinks.py
swaggyjenkins/models/github_repositorypermissions.py
swaggyjenkins/models/github_respository_container.py
swaggyjenkins/models/github_respository_containerlinks.py
swaggyjenkins/models/github_scm.py
swaggyjenkins-3.2.0.dist-info/METADATA
swaggyjenkins-3.2.0.dist-info/WHEEL
swaggyjenkins-3.2.0.dist-info/top_level.txt
swaggyjenkins-3.2.0.dist-info/RECORD
