Metadata-Version: 2.4
Name: swaggyjenkins
Version: 3.2.0
Summary: Swaggy Jenkins
Home-page: https://github.com/oapicf/swaggy-jenkins
Author: OpenAPI Clients Factory
Author-email: blah+oapicf@cliffano.com
Keywords: OpenAPI,OpenAPI-Generator,Swaggy Jenkins
Requires-Dist: urllib3<3.0.0,>=1.25.3
Requires-Dist: python-dateutil>=2.8.2
Requires-Dist: pydantic>=2
Requires-Dist: typing-extensions>=4.7.1
Dynamic: author
Dynamic: author-email
Dynamic: description
Dynamic: description-content-type
Dynamic: home-page
Dynamic: keywords
Dynamic: requires-dist
Dynamic: summary
